pycgraph.cpython-38-darwin.so
pycgraph-3.2.2.dist-info/METADATA
pycgraph-3.2.2.dist-info/WHEEL
pycgraph-3.2.2.dist-info/top_level.txt
pycgraph-3.2.2.dist-info/RECORD
