Metadata-Version: 2.1
Name: pycgraph
Version: 3.2.2
Summary: CGraph with python api wrapper by pybind11
Home-page: https://github.com/ChunelFeng/CGraph
Author: Chunel
Author-email: chunel@foxmail.com
License: MIT
Keywords: pycgraph,CGraph,dag,parallel,airflow,taskflow,workflow,pybind11
Platform: UNKNOWN
Classifier: Development Status :: 5 - Production/Stable
Classifier: Intended Audience :: Developers
Classifier: Programming Language :: Python :: 3
Classifier: Programming Language :: Python :: 3.8
Classifier: Programming Language :: Python :: 3.9
Classifier: Programming Language :: Python :: 3.10
Classifier: Programming Language :: Python :: 3.11
Classifier: Programming Language :: Python :: 3.12
Classifier: Programming Language :: Python :: 3.13
Classifier: Programming Language :: C++
Classifier: Operating System :: Unix
Classifier: Operating System :: MacOS :: MacOS X
Classifier: Operating System :: Microsoft :: Windows
Classifier: License :: OSI Approved :: MIT License
Classifier: Natural Language :: Chinese (Simplified)
Classifier: Natural Language :: English
Requires-Python: >=3.8
